typeapi/__init__.py
typeapi/backport/__init__.py
typeapi/backport/inspect.py
typeapi/future/__init__.py
typeapi/future/astrewrite.py
typeapi/future/astrewrite_test.py
typeapi/future/fake.py
typeapi/future/fake_test.py
typeapi/py.typed
typeapi/typehint.py
typeapi/typehint_test.py
typeapi/utils.py
typeapi/utils_test.py
typeapi-2.2.2.dist-info/LICENSE
typeapi-2.2.2.dist-info/METADATA
typeapi-2.2.2.dist-info/WHEEL
typeapi-2.2.2.dist-info/RECORD
