Metadata-Version: 2.1
Name: typeapi
Version: 2.2.2
Summary: 
License: MIT
Author: Niklas Rosenstein
Author-email: rosensteinniklas@gmail.com
Requires-Python: >=3.8,<4.0
Classifier: License :: OSI Approved :: MIT License
Classifier: Programming Language :: Python :: 3
Classifier: Programming Language :: Python :: 3.8
Classifier: Programming Language :: Python :: 3.9
Classifier: Programming Language :: Python :: 3.10
Classifier: Programming Language :: Python :: 3.11
Classifier: Programming Language :: Python :: 3.12
Requires-Dist: typing-extensions (>=3.0.0)
Project-URL: Bug Tracker, https://github.com/NiklasRosenstein/python-typeapi/issues
Project-URL: Documentation, https://niklasrosenstein.github.io/python-typeapi/
Project-URL: Homepage, https://github.com/NiklasRosenstein/python-typeapi
